<?xml version="1.0" encoding="UTF-8"?>
<response>
  <status>success</status>
  <items_returned>182</items_returned>
  <items_available>182</items_available>
  <first_item_position>0</first_item_position>
  <result>
    <size_fact>
      <month>1998-06-01T00:00:00Z</month>
      <code>2064</code>
      <comments>297</comments>
      <blanks>552</blanks>
      <comment_ratio>0.12579415501906</comment_ratio>
      <commits>42</commits>
      <man_months>3</man_months>
    </size_fact>
    <size_fact>
      <month>1998-07-01T00:00:00Z</month>
      <code>2222</code>
      <comments>427</comments>
      <blanks>600</blanks>
      <comment_ratio>0.161192902982257</comment_ratio>
      <commits>47</commits>
      <man_months>4</man_months>
    </size_fact>
    <size_fact>
      <month>1998-08-01T00:00:00Z</month>
      <code>2222</code>
      <comments>427</comments>
      <blanks>600</blanks>
      <comment_ratio>0.161192902982257</comment_ratio>
      <commits>47</commits>
      <man_months>4</man_months>
    </size_fact>
    <size_fact>
      <month>1998-09-01T00:00:00Z</month>
      <code>2222</code>
      <comments>427</comments>
      <blanks>600</blanks>
      <comment_ratio>0.161192902982257</comment_ratio>
      <commits>48</commits>
      <man_months>5</man_months>
    </size_fact>
    <size_fact>
      <month>1998-10-01T00:00:00Z</month>
      <code>2222</code>
      <comments>427</comments>
      <blanks>600</blanks>
      <comment_ratio>0.161192902982257</comment_ratio>
      <commits>48</commits>
      <man_months>5</man_months>
    </size_fact>
    <size_fact>
      <month>1998-11-01T00:00:00Z</month>
      <code>2264</code>
      <comments>423</comments>
      <blanks>610</blanks>
      <comment_ratio>0.157424637141794</comment_ratio>
      <commits>49</commits>
      <man_months>6</man_months>
    </size_fact>
    <size_fact>
      <month>1998-12-01T00:00:00Z</month>
      <code>2264</code>
      <comments>423</comments>
      <blanks>610</blanks>
      <comment_ratio>0.157424637141794</comment_ratio>
      <commits>49</commits>
      <man_months>6</man_months>
    </size_fact>
    <size_fact>
      <month>1999-01-01T00:00:00Z</month>
      <code>2320</code>
      <comments>430</comments>
      <blanks>624</blanks>
      <comment_ratio>0.156363636363636</comment_ratio>
      <commits>53</commits>
      <man_months>8</man_months>
    </size_fact>
    <size_fact>
      <month>1999-02-01T00:00:00Z</month>
      <code>2320</code>
      <comments>430</comments>
      <blanks>624</blanks>
      <comment_ratio>0.156363636363636</comment_ratio>
      <commits>53</commits>
      <man_months>8</man_months>
    </size_fact>
    <size_fact>
      <month>1999-03-01T00:00:00Z</month>
      <code>2736</code>
      <comments>490</comments>
      <blanks>727</blanks>
      <comment_ratio>0.151890886546807</comment_ratio>
      <commits>57</commits>
      <man_months>11</man_months>
    </size_fact>
    <size_fact>
      <month>1999-04-01T00:00:00Z</month>
      <code>2748</code>
      <comments>497</comments>
      <blanks>730</blanks>
      <comment_ratio>0.153158705701079</comment_ratio>
      <commits>66</commits>
      <man_months>14</man_months>
    </size_fact>
    <size_fact>
      <month>1999-05-01T00:00:00Z</month>
      <code>2748</code>
      <comments>497</comments>
      <blanks>730</blanks>
      <comment_ratio>0.153158705701079</comment_ratio>
      <commits>66</commits>
      <man_months>14</man_months>
    </size_fact>
    <size_fact>
      <month>1999-06-01T00:00:00Z</month>
      <code>2748</code>
      <comments>497</comments>
      <blanks>730</blanks>
      <comment_ratio>0.153158705701079</comment_ratio>
      <commits>66</commits>
      <man_months>14</man_months>
    </size_fact>
    <size_fact>
      <month>1999-07-01T00:00:00Z</month>
      <code>2751</code>
      <comments>497</comments>
      <blanks>731</blanks>
      <comment_ratio>0.15301724137931</comment_ratio>
      <commits>67</commits>
      <man_months>15</man_months>
    </size_fact>
    <size_fact>
      <month>1999-08-01T00:00:00Z</month>
      <code>2751</code>
      <comments>497</comments>
      <blanks>731</blanks>
      <comment_ratio>0.15301724137931</comment_ratio>
      <commits>68</commits>
      <man_months>16</man_months>
    </size_fact>
    <size_fact>
      <month>1999-09-01T00:00:00Z</month>
      <code>2803</code>
      <comments>494</comments>
      <blanks>738</blanks>
      <comment_ratio>0.149833181680315</comment_ratio>
      <commits>72</commits>
      <man_months>18</man_months>
    </size_fact>
    <size_fact>
      <month>1999-10-01T00:00:00Z</month>
      <code>2821</code>
      <comments>494</comments>
      <blanks>740</blanks>
      <comment_ratio>0.149019607843137</comment_ratio>
      <commits>81</commits>
      <man_months>21</man_months>
    </size_fact>
    <size_fact>
      <month>1999-11-01T00:00:00Z</month>
      <code>2833</code>
      <comments>494</comments>
      <blanks>740</blanks>
      <comment_ratio>0.148482116020439</comment_ratio>
      <commits>84</commits>
      <man_months>22</man_months>
    </size_fact>
    <size_fact>
      <month>1999-12-01T00:00:00Z</month>
      <code>2833</code>
      <comments>494</comments>
      <blanks>740</blanks>
      <comment_ratio>0.148482116020439</comment_ratio>
      <commits>84</commits>
      <man_months>22</man_months>
    </size_fact>
    <size_fact>
      <month>2000-01-01T00:00:00Z</month>
      <code>2833</code>
      <comments>494</comments>
      <blanks>740</blanks>
      <comment_ratio>0.148482116020439</comment_ratio>
      <commits>84</commits>
      <man_months>22</man_months>
    </size_fact>
    <size_fact>
      <month>2000-02-01T00:00:00Z</month>
      <code>2833</code>
      <comments>494</comments>
      <blanks>740</blanks>
      <comment_ratio>0.148482116020439</comment_ratio>
      <commits>84</commits>
      <man_months>22</man_months>
    </size_fact>
    <size_fact>
      <month>2000-03-01T00:00:00Z</month>
      <code>2833</code>
      <comments>494</comments>
      <blanks>740</blanks>
      <comment_ratio>0.148482116020439</comment_ratio>
      <commits>85</commits>
      <man_months>23</man_months>
    </size_fact>
    <size_fact>
      <month>2000-04-01T00:00:00Z</month>
      <code>2833</code>
      <comments>494</comments>
      <blanks>740</blanks>
      <comment_ratio>0.148482116020439</comment_ratio>
      <commits>85</commits>
      <man_months>23</man_months>
    </size_fact>
    <size_fact>
      <month>2000-05-01T00:00:00Z</month>
      <code>2833</code>
      <comments>494</comments>
      <blanks>740</blanks>
      <comment_ratio>0.148482116020439</comment_ratio>
      <commits>85</commits>
      <man_months>23</man_months>
    </size_fact>
    <size_fact>
      <month>2000-06-01T00:00:00Z</month>
      <code>2833</code>
      <comments>494</comments>
      <blanks>740</blanks>
      <comment_ratio>0.148482116020439</comment_ratio>
      <commits>85</commits>
      <man_months>23</man_months>
    </size_fact>
    <size_fact>
      <month>2000-07-01T00:00:00Z</month>
      <code>2833</code>
      <comments>494</comments>
      <blanks>740</blanks>
      <comment_ratio>0.148482116020439</comment_ratio>
      <commits>85</commits>
      <man_months>23</man_months>
    </size_fact>
    <size_fact>
      <month>2000-08-01T00:00:00Z</month>
      <code>2833</code>
      <comments>494</comments>
      <blanks>740</blanks>
      <comment_ratio>0.148482116020439</comment_ratio>
      <commits>87</commits>
      <man_months>24</man_months>
    </size_fact>
    <size_fact>
      <month>2000-09-01T00:00:00Z</month>
      <code>2833</code>
      <comments>494</comments>
      <blanks>740</blanks>
      <comment_ratio>0.148482116020439</comment_ratio>
      <commits>87</commits>
      <man_months>24</man_months>
    </size_fact>
    <size_fact>
      <month>2000-10-01T00:00:00Z</month>
      <code>2833</code>
      <comments>494</comments>
      <blanks>740</blanks>
      <comment_ratio>0.148482116020439</comment_ratio>
      <commits>87</commits>
      <man_months>24</man_months>
    </size_fact>
    <size_fact>
      <month>2000-11-01T00:00:00Z</month>
      <code>2833</code>
      <comments>494</comments>
      <blanks>740</blanks>
      <comment_ratio>0.148482116020439</comment_ratio>
      <commits>87</commits>
      <man_months>24</man_months>
    </size_fact>
    <size_fact>
      <month>2000-12-01T00:00:00Z</month>
      <code>2833</code>
      <comments>494</comments>
      <blanks>740</blanks>
      <comment_ratio>0.148482116020439</comment_ratio>
      <commits>87</commits>
      <man_months>24</man_months>
    </size_fact>
    <size_fact>
      <month>2001-01-01T00:00:00Z</month>
      <code>2833</code>
      <comments>494</comments>
      <blanks>740</blanks>
      <comment_ratio>0.148482116020439</comment_ratio>
      <commits>87</commits>
      <man_months>24</man_months>
    </size_fact>
    <size_fact>
      <month>2001-02-01T00:00:00Z</month>
      <code>2833</code>
      <comments>494</comments>
      <blanks>740</blanks>
      <comment_ratio>0.148482116020439</comment_ratio>
      <commits>88</commits>
      <man_months>25</man_months>
    </size_fact>
    <size_fact>
      <month>2001-03-01T00:00:00Z</month>
      <code>2834</code>
      <comments>494</comments>
      <blanks>740</blanks>
      <comment_ratio>0.1484375</comment_ratio>
      <commits>89</commits>
      <man_months>26</man_months>
    </size_fact>
    <size_fact>
      <month>2001-04-01T00:00:00Z</month>
      <code>2834</code>
      <comments>494</comments>
      <blanks>740</blanks>
      <comment_ratio>0.1484375</comment_ratio>
      <commits>89</commits>
      <man_months>26</man_months>
    </size_fact>
    <size_fact>
      <month>2001-05-01T00:00:00Z</month>
      <code>2834</code>
      <comments>494</comments>
      <blanks>740</blanks>
      <comment_ratio>0.1484375</comment_ratio>
      <commits>91</commits>
      <man_months>28</man_months>
    </size_fact>
    <size_fact>
      <month>2001-06-01T00:00:00Z</month>
      <code>2834</code>
      <comments>494</comments>
      <blanks>740</blanks>
      <comment_ratio>0.1484375</comment_ratio>
      <commits>91</commits>
      <man_months>28</man_months>
    </size_fact>
    <size_fact>
      <month>2001-07-01T00:00:00Z</month>
      <code>2834</code>
      <comments>494</comments>
      <blanks>740</blanks>
      <comment_ratio>0.1484375</comment_ratio>
      <commits>93</commits>
      <man_months>30</man_months>
    </size_fact>
    <size_fact>
      <month>2001-08-01T00:00:00Z</month>
      <code>2834</code>
      <comments>494</comments>
      <blanks>739</blanks>
      <comment_ratio>0.1484375</comment_ratio>
      <commits>94</commits>
      <man_months>31</man_months>
    </size_fact>
    <size_fact>
      <month>2001-09-01T00:00:00Z</month>
      <code>2834</code>
      <comments>494</comments>
      <blanks>739</blanks>
      <comment_ratio>0.1484375</comment_ratio>
      <commits>94</commits>
      <man_months>31</man_months>
    </size_fact>
    <size_fact>
      <month>2001-10-01T00:00:00Z</month>
      <code>2844</code>
      <comments>494</comments>
      <blanks>739</blanks>
      <comment_ratio>0.147992810065908</comment_ratio>
      <commits>95</commits>
      <man_months>32</man_months>
    </size_fact>
    <size_fact>
      <month>2001-11-01T00:00:00Z</month>
      <code>2844</code>
      <comments>494</comments>
      <blanks>739</blanks>
      <comment_ratio>0.147992810065908</comment_ratio>
      <commits>95</commits>
      <man_months>32</man_months>
    </size_fact>
    <size_fact>
      <month>2001-12-01T00:00:00Z</month>
      <code>2844</code>
      <comments>494</comments>
      <blanks>739</blanks>
      <comment_ratio>0.147992810065908</comment_ratio>
      <commits>95</commits>
      <man_months>32</man_months>
    </size_fact>
    <size_fact>
      <month>2002-01-01T00:00:00Z</month>
      <code>2844</code>
      <comments>494</comments>
      <blanks>739</blanks>
      <comment_ratio>0.147992810065908</comment_ratio>
      <commits>95</commits>
      <man_months>32</man_months>
    </size_fact>
    <size_fact>
      <month>2002-02-01T00:00:00Z</month>
      <code>2844</code>
      <comments>494</comments>
      <blanks>739</blanks>
      <comment_ratio>0.147992810065908</comment_ratio>
      <commits>95</commits>
      <man_months>32</man_months>
    </size_fact>
    <size_fact>
      <month>2002-03-01T00:00:00Z</month>
      <code>2844</code>
      <comments>494</comments>
      <blanks>739</blanks>
      <comment_ratio>0.147992810065908</comment_ratio>
      <commits>95</commits>
      <man_months>32</man_months>
    </size_fact>
    <size_fact>
      <month>2002-04-01T00:00:00Z</month>
      <code>2844</code>
      <comments>494</comments>
      <blanks>739</blanks>
      <comment_ratio>0.147992810065908</comment_ratio>
      <commits>95</commits>
      <man_months>32</man_months>
    </size_fact>
    <size_fact>
      <month>2002-05-01T00:00:00Z</month>
      <code>2844</code>
      <comments>494</comments>
      <blanks>739</blanks>
      <comment_ratio>0.147992810065908</comment_ratio>
      <commits>95</commits>
      <man_months>32</man_months>
    </size_fact>
    <size_fact>
      <month>2002-06-01T00:00:00Z</month>
      <code>2844</code>
      <comments>494</comments>
      <blanks>739</blanks>
      <comment_ratio>0.147992810065908</comment_ratio>
      <commits>95</commits>
      <man_months>32</man_months>
    </size_fact>
    <size_fact>
      <month>2002-07-01T00:00:00Z</month>
      <code>2844</code>
      <comments>494</comments>
      <blanks>739</blanks>
      <comment_ratio>0.147992810065908</comment_ratio>
      <commits>95</commits>
      <man_months>32</man_months>
    </size_fact>
    <size_fact>
      <month>2002-08-01T00:00:00Z</month>
      <code>2844</code>
      <comments>494</comments>
      <blanks>740</blanks>
      <comment_ratio>0.147992810065908</comment_ratio>
      <commits>97</commits>
      <man_months>34</man_months>
    </size_fact>
    <size_fact>
      <month>2002-09-01T00:00:00Z</month>
      <code>2844</code>
      <comments>494</comments>
      <blanks>740</blanks>
      <comment_ratio>0.147992810065908</comment_ratio>
      <commits>97</commits>
      <man_months>34</man_months>
    </size_fact>
    <size_fact>
      <month>2002-10-01T00:00:00Z</month>
      <code>2844</code>
      <comments>494</comments>
      <blanks>740</blanks>
      <comment_ratio>0.147992810065908</comment_ratio>
      <commits>97</commits>
      <man_months>34</man_months>
    </size_fact>
    <size_fact>
      <month>2002-11-01T00:00:00Z</month>
      <code>2844</code>
      <comments>494</comments>
      <blanks>740</blanks>
      <comment_ratio>0.147992810065908</comment_ratio>
      <commits>97</commits>
      <man_months>34</man_months>
    </size_fact>
    <size_fact>
      <month>2002-12-01T00:00:00Z</month>
      <code>2844</code>
      <comments>494</comments>
      <blanks>740</blanks>
      <comment_ratio>0.147992810065908</comment_ratio>
      <commits>97</commits>
      <man_months>34</man_months>
    </size_fact>
    <size_fact>
      <month>2003-01-01T00:00:00Z</month>
      <code>2844</code>
      <comments>494</comments>
      <blanks>740</blanks>
      <comment_ratio>0.147992810065908</comment_ratio>
      <commits>97</commits>
      <man_months>34</man_months>
    </size_fact>
    <size_fact>
      <month>2003-02-01T00:00:00Z</month>
      <code>2844</code>
      <comments>494</comments>
      <blanks>740</blanks>
      <comment_ratio>0.147992810065908</comment_ratio>
      <commits>97</commits>
      <man_months>34</man_months>
    </size_fact>
    <size_fact>
      <month>2003-03-01T00:00:00Z</month>
      <code>2844</code>
      <comments>494</comments>
      <blanks>740</blanks>
      <comment_ratio>0.147992810065908</comment_ratio>
      <commits>97</commits>
      <man_months>34</man_months>
    </size_fact>
    <size_fact>
      <month>2003-04-01T00:00:00Z</month>
      <code>2844</code>
      <comments>494</comments>
      <blanks>740</blanks>
      <comment_ratio>0.147992810065908</comment_ratio>
      <commits>97</commits>
      <man_months>34</man_months>
    </size_fact>
    <size_fact>
      <month>2003-05-01T00:00:00Z</month>
      <code>2844</code>
      <comments>494</comments>
      <blanks>740</blanks>
      <comment_ratio>0.147992810065908</comment_ratio>
      <commits>97</commits>
      <man_months>34</man_months>
    </size_fact>
    <size_fact>
      <month>2003-06-01T00:00:00Z</month>
      <code>2844</code>
      <comments>494</comments>
      <blanks>740</blanks>
      <comment_ratio>0.147992810065908</comment_ratio>
      <commits>97</commits>
      <man_months>34</man_months>
    </size_fact>
    <size_fact>
      <month>2003-07-01T00:00:00Z</month>
      <code>2844</code>
      <comments>494</comments>
      <blanks>740</blanks>
      <comment_ratio>0.147992810065908</comment_ratio>
      <commits>98</commits>
      <man_months>35</man_months>
    </size_fact>
    <size_fact>
      <month>2003-08-01T00:00:00Z</month>
      <code>2844</code>
      <comments>494</comments>
      <blanks>740</blanks>
      <comment_ratio>0.147992810065908</comment_ratio>
      <commits>98</commits>
      <man_months>35</man_months>
    </size_fact>
    <size_fact>
      <month>2003-09-01T00:00:00Z</month>
      <code>2844</code>
      <comments>494</comments>
      <blanks>740</blanks>
      <comment_ratio>0.147992810065908</comment_ratio>
      <commits>99</commits>
      <man_months>36</man_months>
    </size_fact>
    <size_fact>
      <month>2003-10-01T00:00:00Z</month>
      <code>2844</code>
      <comments>494</comments>
      <blanks>740</blanks>
      <comment_ratio>0.147992810065908</comment_ratio>
      <commits>99</commits>
      <man_months>36</man_months>
    </size_fact>
    <size_fact>
      <month>2003-11-01T00:00:00Z</month>
      <code>2844</code>
      <comments>494</comments>
      <blanks>740</blanks>
      <comment_ratio>0.147992810065908</comment_ratio>
      <commits>99</commits>
      <man_months>36</man_months>
    </size_fact>
    <size_fact>
      <month>2003-12-01T00:00:00Z</month>
      <code>2844</code>
      <comments>494</comments>
      <blanks>740</blanks>
      <comment_ratio>0.147992810065908</comment_ratio>
      <commits>99</commits>
      <man_months>36</man_months>
    </size_fact>
    <size_fact>
      <month>2004-01-01T00:00:00Z</month>
      <code>2844</code>
      <comments>494</comments>
      <blanks>740</blanks>
      <comment_ratio>0.147992810065908</comment_ratio>
      <commits>99</commits>
      <man_months>36</man_months>
    </size_fact>
    <size_fact>
      <month>2004-02-01T00:00:00Z</month>
      <code>2850</code>
      <comments>495</comments>
      <blanks>741</blanks>
      <comment_ratio>0.147982062780269</comment_ratio>
      <commits>100</commits>
      <man_months>37</man_months>
    </size_fact>
    <size_fact>
      <month>2004-03-01T00:00:00Z</month>
      <code>2852</code>
      <comments>495</comments>
      <blanks>741</blanks>
      <comment_ratio>0.147893636092023</comment_ratio>
      <commits>101</commits>
      <man_months>38</man_months>
    </size_fact>
    <size_fact>
      <month>2004-04-01T00:00:00Z</month>
      <code>2853</code>
      <comments>495</comments>
      <blanks>741</blanks>
      <comment_ratio>0.147849462365591</comment_ratio>
      <commits>102</commits>
      <man_months>39</man_months>
    </size_fact>
    <size_fact>
      <month>2004-05-01T00:00:00Z</month>
      <code>2853</code>
      <comments>495</comments>
      <blanks>741</blanks>
      <comment_ratio>0.147849462365591</comment_ratio>
      <commits>102</commits>
      <man_months>39</man_months>
    </size_fact>
    <size_fact>
      <month>2004-06-01T00:00:00Z</month>
      <code>2853</code>
      <comments>495</comments>
      <blanks>741</blanks>
      <comment_ratio>0.147849462365591</comment_ratio>
      <commits>102</commits>
      <man_months>39</man_months>
    </size_fact>
    <size_fact>
      <month>2004-07-01T00:00:00Z</month>
      <code>2853</code>
      <comments>495</comments>
      <blanks>741</blanks>
      <comment_ratio>0.147849462365591</comment_ratio>
      <commits>103</commits>
      <man_months>40</man_months>
    </size_fact>
    <size_fact>
      <month>2004-08-01T00:00:00Z</month>
      <code>2853</code>
      <comments>495</comments>
      <blanks>741</blanks>
      <comment_ratio>0.147849462365591</comment_ratio>
      <commits>103</commits>
      <man_months>40</man_months>
    </size_fact>
    <size_fact>
      <month>2004-09-01T00:00:00Z</month>
      <code>2853</code>
      <comments>495</comments>
      <blanks>741</blanks>
      <comment_ratio>0.147849462365591</comment_ratio>
      <commits>103</commits>
      <man_months>40</man_months>
    </size_fact>
    <size_fact>
      <month>2004-10-01T00:00:00Z</month>
      <code>2853</code>
      <comments>495</comments>
      <blanks>741</blanks>
      <comment_ratio>0.147849462365591</comment_ratio>
      <commits>103</commits>
      <man_months>40</man_months>
    </size_fact>
    <size_fact>
      <month>2004-11-01T00:00:00Z</month>
      <code>2853</code>
      <comments>495</comments>
      <blanks>741</blanks>
      <comment_ratio>0.147849462365591</comment_ratio>
      <commits>103</commits>
      <man_months>40</man_months>
    </size_fact>
    <size_fact>
      <month>2004-12-01T00:00:00Z</month>
      <code>2853</code>
      <comments>495</comments>
      <blanks>741</blanks>
      <comment_ratio>0.147849462365591</comment_ratio>
      <commits>103</commits>
      <man_months>40</man_months>
    </size_fact>
    <size_fact>
      <month>2005-01-01T00:00:00Z</month>
      <code>2853</code>
      <comments>495</comments>
      <blanks>741</blanks>
      <comment_ratio>0.147849462365591</comment_ratio>
      <commits>105</commits>
      <man_months>41</man_months>
    </size_fact>
    <size_fact>
      <month>2005-02-01T00:00:00Z</month>
      <code>2853</code>
      <comments>495</comments>
      <blanks>741</blanks>
      <comment_ratio>0.147849462365591</comment_ratio>
      <commits>105</commits>
      <man_months>41</man_months>
    </size_fact>
    <size_fact>
      <month>2005-03-01T00:00:00Z</month>
      <code>2853</code>
      <comments>495</comments>
      <blanks>741</blanks>
      <comment_ratio>0.147849462365591</comment_ratio>
      <commits>105</commits>
      <man_months>41</man_months>
    </size_fact>
    <size_fact>
      <month>2005-04-01T00:00:00Z</month>
      <code>2853</code>
      <comments>495</comments>
      <blanks>741</blanks>
      <comment_ratio>0.147849462365591</comment_ratio>
      <commits>105</commits>
      <man_months>41</man_months>
    </size_fact>
    <size_fact>
      <month>2005-05-01T00:00:00Z</month>
      <code>2853</code>
      <comments>495</comments>
      <blanks>741</blanks>
      <comment_ratio>0.147849462365591</comment_ratio>
      <commits>105</commits>
      <man_months>41</man_months>
    </size_fact>
    <size_fact>
      <month>2005-06-01T00:00:00Z</month>
      <code>2853</code>
      <comments>495</comments>
      <blanks>741</blanks>
      <comment_ratio>0.147849462365591</comment_ratio>
      <commits>105</commits>
      <man_months>41</man_months>
    </size_fact>
    <size_fact>
      <month>2005-07-01T00:00:00Z</month>
      <code>2853</code>
      <comments>495</comments>
      <blanks>741</blanks>
      <comment_ratio>0.147849462365591</comment_ratio>
      <commits>105</commits>
      <man_months>41</man_months>
    </size_fact>
    <size_fact>
      <month>2005-08-01T00:00:00Z</month>
      <code>2853</code>
      <comments>495</comments>
      <blanks>741</blanks>
      <comment_ratio>0.147849462365591</comment_ratio>
      <commits>105</commits>
      <man_months>41</man_months>
    </size_fact>
    <size_fact>
      <month>2005-09-01T00:00:00Z</month>
      <code>2853</code>
      <comments>495</comments>
      <blanks>741</blanks>
      <comment_ratio>0.147849462365591</comment_ratio>
      <commits>105</commits>
      <man_months>41</man_months>
    </size_fact>
    <size_fact>
      <month>2005-10-01T00:00:00Z</month>
      <code>2853</code>
      <comments>495</comments>
      <blanks>741</blanks>
      <comment_ratio>0.147849462365591</comment_ratio>
      <commits>105</commits>
      <man_months>41</man_months>
    </size_fact>
    <size_fact>
      <month>2005-11-01T00:00:00Z</month>
      <code>2864</code>
      <comments>496</comments>
      <blanks>742</blanks>
      <comment_ratio>0.147619047619048</comment_ratio>
      <commits>107</commits>
      <man_months>42</man_months>
    </size_fact>
    <size_fact>
      <month>2005-12-01T00:00:00Z</month>
      <code>2915</code>
      <comments>496</comments>
      <blanks>744</blanks>
      <comment_ratio>0.145411902667839</comment_ratio>
      <commits>111</commits>
      <man_months>43</man_months>
    </size_fact>
    <size_fact>
      <month>2006-01-01T00:00:00Z</month>
      <code>2915</code>
      <comments>496</comments>
      <blanks>744</blanks>
      <comment_ratio>0.145411902667839</comment_ratio>
      <commits>111</commits>
      <man_months>43</man_months>
    </size_fact>
    <size_fact>
      <month>2006-02-01T00:00:00Z</month>
      <code>2915</code>
      <comments>496</comments>
      <blanks>744</blanks>
      <comment_ratio>0.145411902667839</comment_ratio>
      <commits>112</commits>
      <man_months>44</man_months>
    </size_fact>
    <size_fact>
      <month>2006-03-01T00:00:00Z</month>
      <code>2915</code>
      <comments>496</comments>
      <blanks>744</blanks>
      <comment_ratio>0.145411902667839</comment_ratio>
      <commits>112</commits>
      <man_months>44</man_months>
    </size_fact>
    <size_fact>
      <month>2006-04-01T00:00:00Z</month>
      <code>2915</code>
      <comments>496</comments>
      <blanks>744</blanks>
      <comment_ratio>0.145411902667839</comment_ratio>
      <commits>112</commits>
      <man_months>44</man_months>
    </size_fact>
    <size_fact>
      <month>2006-05-01T00:00:00Z</month>
      <code>2915</code>
      <comments>496</comments>
      <blanks>744</blanks>
      <comment_ratio>0.145411902667839</comment_ratio>
      <commits>112</commits>
      <man_months>44</man_months>
    </size_fact>
    <size_fact>
      <month>2006-06-01T00:00:00Z</month>
      <code>3088</code>
      <comments>519</comments>
      <blanks>791</blanks>
      <comment_ratio>0.143886886609371</comment_ratio>
      <commits>113</commits>
      <man_months>45</man_months>
    </size_fact>
    <size_fact>
      <month>2006-07-01T00:00:00Z</month>
      <code>3088</code>
      <comments>519</comments>
      <blanks>791</blanks>
      <comment_ratio>0.143886886609371</comment_ratio>
      <commits>113</commits>
      <man_months>45</man_months>
    </size_fact>
    <size_fact>
      <month>2006-08-01T00:00:00Z</month>
      <code>3088</code>
      <comments>519</comments>
      <blanks>791</blanks>
      <comment_ratio>0.143886886609371</comment_ratio>
      <commits>113</commits>
      <man_months>45</man_months>
    </size_fact>
    <size_fact>
      <month>2006-09-01T00:00:00Z</month>
      <code>3830</code>
      <comments>596</comments>
      <blanks>918</blanks>
      <comment_ratio>0.134658834161771</comment_ratio>
      <commits>128</commits>
      <man_months>51</man_months>
    </size_fact>
    <size_fact>
      <month>2006-10-01T00:00:00Z</month>
      <code>3830</code>
      <comments>596</comments>
      <blanks>918</blanks>
      <comment_ratio>0.134658834161771</comment_ratio>
      <commits>128</commits>
      <man_months>51</man_months>
    </size_fact>
    <size_fact>
      <month>2006-11-01T00:00:00Z</month>
      <code>3830</code>
      <comments>596</comments>
      <blanks>918</blanks>
      <comment_ratio>0.134658834161771</comment_ratio>
      <commits>128</commits>
      <man_months>51</man_months>
    </size_fact>
    <size_fact>
      <month>2006-12-01T00:00:00Z</month>
      <code>3834</code>
      <comments>596</comments>
      <blanks>918</blanks>
      <comment_ratio>0.134537246049661</comment_ratio>
      <commits>133</commits>
      <man_months>53</man_months>
    </size_fact>
    <size_fact>
      <month>2007-01-01T00:00:00Z</month>
      <code>3835</code>
      <comments>596</comments>
      <blanks>918</blanks>
      <comment_ratio>0.134506883322049</comment_ratio>
      <commits>134</commits>
      <man_months>54</man_months>
    </size_fact>
    <size_fact>
      <month>2007-02-01T00:00:00Z</month>
      <code>3835</code>
      <comments>596</comments>
      <blanks>918</blanks>
      <comment_ratio>0.134506883322049</comment_ratio>
      <commits>134</commits>
      <man_months>54</man_months>
    </size_fact>
    <size_fact>
      <month>2007-03-01T00:00:00Z</month>
      <code>3835</code>
      <comments>596</comments>
      <blanks>918</blanks>
      <comment_ratio>0.134506883322049</comment_ratio>
      <commits>134</commits>
      <man_months>54</man_months>
    </size_fact>
    <size_fact>
      <month>2007-04-01T00:00:00Z</month>
      <code>3835</code>
      <comments>596</comments>
      <blanks>918</blanks>
      <comment_ratio>0.134506883322049</comment_ratio>
      <commits>134</commits>
      <man_months>54</man_months>
    </size_fact>
    <size_fact>
      <month>2007-05-01T00:00:00Z</month>
      <code>3835</code>
      <comments>596</comments>
      <blanks>918</blanks>
      <comment_ratio>0.134506883322049</comment_ratio>
      <commits>134</commits>
      <man_months>54</man_months>
    </size_fact>
    <size_fact>
      <month>2007-06-01T00:00:00Z</month>
      <code>3835</code>
      <comments>596</comments>
      <blanks>918</blanks>
      <comment_ratio>0.134506883322049</comment_ratio>
      <commits>134</commits>
      <man_months>54</man_months>
    </size_fact>
    <size_fact>
      <month>2007-07-01T00:00:00Z</month>
      <code>3835</code>
      <comments>596</comments>
      <blanks>918</blanks>
      <comment_ratio>0.134506883322049</comment_ratio>
      <commits>134</commits>
      <man_months>54</man_months>
    </size_fact>
    <size_fact>
      <month>2007-08-01T00:00:00Z</month>
      <code>3835</code>
      <comments>596</comments>
      <blanks>918</blanks>
      <comment_ratio>0.134506883322049</comment_ratio>
      <commits>134</commits>
      <man_months>54</man_months>
    </size_fact>
    <size_fact>
      <month>2007-09-01T00:00:00Z</month>
      <code>3835</code>
      <comments>596</comments>
      <blanks>918</blanks>
      <comment_ratio>0.134506883322049</comment_ratio>
      <commits>134</commits>
      <man_months>54</man_months>
    </size_fact>
    <size_fact>
      <month>2007-10-01T00:00:00Z</month>
      <code>3835</code>
      <comments>596</comments>
      <blanks>918</blanks>
      <comment_ratio>0.134506883322049</comment_ratio>
      <commits>134</commits>
      <man_months>54</man_months>
    </size_fact>
    <size_fact>
      <month>2007-11-01T00:00:00Z</month>
      <code>3835</code>
      <comments>596</comments>
      <blanks>918</blanks>
      <comment_ratio>0.134506883322049</comment_ratio>
      <commits>136</commits>
      <man_months>55</man_months>
    </size_fact>
    <size_fact>
      <month>2007-12-01T00:00:00Z</month>
      <code>3835</code>
      <comments>596</comments>
      <blanks>918</blanks>
      <comment_ratio>0.134506883322049</comment_ratio>
      <commits>136</commits>
      <man_months>55</man_months>
    </size_fact>
    <size_fact>
      <month>2008-01-01T00:00:00Z</month>
      <code>3835</code>
      <comments>596</comments>
      <blanks>918</blanks>
      <comment_ratio>0.134506883322049</comment_ratio>
      <commits>136</commits>
      <man_months>55</man_months>
    </size_fact>
    <size_fact>
      <month>2008-02-01T00:00:00Z</month>
      <code>3835</code>
      <comments>596</comments>
      <blanks>918</blanks>
      <comment_ratio>0.134506883322049</comment_ratio>
      <commits>136</commits>
      <man_months>55</man_months>
    </size_fact>
    <size_fact>
      <month>2008-03-01T00:00:00Z</month>
      <code>11339</code>
      <comments>1410</comments>
      <blanks>2251</blanks>
      <comment_ratio>0.110596909561534</comment_ratio>
      <commits>158</commits>
      <man_months>63</man_months>
    </size_fact>
    <size_fact>
      <month>2008-04-01T00:00:00Z</month>
      <code>10979</code>
      <comments>1405</comments>
      <blanks>2137</blanks>
      <comment_ratio>0.113452842377261</comment_ratio>
      <commits>160</commits>
      <man_months>65</man_months>
    </size_fact>
    <size_fact>
      <month>2008-05-01T00:00:00Z</month>
      <code>11015</code>
      <comments>1424</comments>
      <blanks>2137</blanks>
      <comment_ratio>0.114478655840502</comment_ratio>
      <commits>181</commits>
      <man_months>72</man_months>
    </size_fact>
    <size_fact>
      <month>2008-06-01T00:00:00Z</month>
      <code>11015</code>
      <comments>1424</comments>
      <blanks>2137</blanks>
      <comment_ratio>0.114478655840502</comment_ratio>
      <commits>181</commits>
      <man_months>72</man_months>
    </size_fact>
    <size_fact>
      <month>2008-07-01T00:00:00Z</month>
      <code>11050</code>
      <comments>1409</comments>
      <blanks>2090</blanks>
      <comment_ratio>0.11309093827755</comment_ratio>
      <commits>239</commits>
      <man_months>80</man_months>
    </size_fact>
    <size_fact>
      <month>2008-08-01T00:00:00Z</month>
      <code>11074</code>
      <comments>1407</comments>
      <blanks>2088</blanks>
      <comment_ratio>0.112731351654515</comment_ratio>
      <commits>256</commits>
      <man_months>84</man_months>
    </size_fact>
    <size_fact>
      <month>2008-09-01T00:00:00Z</month>
      <code>11161</code>
      <comments>1413</comments>
      <blanks>2097</blanks>
      <comment_ratio>0.112374741530142</comment_ratio>
      <commits>273</commits>
      <man_months>86</man_months>
    </size_fact>
    <size_fact>
      <month>2008-10-01T00:00:00Z</month>
      <code>11436</code>
      <comments>1429</comments>
      <blanks>2143</blanks>
      <comment_ratio>0.111076564321803</comment_ratio>
      <commits>287</commits>
      <man_months>87</man_months>
    </size_fact>
    <size_fact>
      <month>2008-11-01T00:00:00Z</month>
      <code>12818</code>
      <comments>1587</comments>
      <blanks>2249</blanks>
      <comment_ratio>0.110170079833391</comment_ratio>
      <commits>334</commits>
      <man_months>92</man_months>
    </size_fact>
    <size_fact>
      <month>2008-12-01T00:00:00Z</month>
      <code>12905</code>
      <comments>1587</comments>
      <blanks>2251</blanks>
      <comment_ratio>0.109508694452112</comment_ratio>
      <commits>364</commits>
      <man_months>97</man_months>
    </size_fact>
    <size_fact>
      <month>2009-01-01T00:00:00Z</month>
      <code>12950</code>
      <comments>1593</comments>
      <blanks>2265</blanks>
      <comment_ratio>0.109537234408306</comment_ratio>
      <commits>368</commits>
      <man_months>98</man_months>
    </size_fact>
    <size_fact>
      <month>2009-02-01T00:00:00Z</month>
      <code>12963</code>
      <comments>1598</comments>
      <blanks>2264</blanks>
      <comment_ratio>0.109745209807019</comment_ratio>
      <commits>374</commits>
      <man_months>103</man_months>
    </size_fact>
    <size_fact>
      <month>2009-03-01T00:00:00Z</month>
      <code>12957</code>
      <comments>1598</comments>
      <blanks>2264</blanks>
      <comment_ratio>0.109790450017176</comment_ratio>
      <commits>375</commits>
      <man_months>104</man_months>
    </size_fact>
    <size_fact>
      <month>2009-04-01T00:00:00Z</month>
      <code>12951</code>
      <comments>1604</comments>
      <blanks>2266</blanks>
      <comment_ratio>0.110202679491584</comment_ratio>
      <commits>381</commits>
      <man_months>107</man_months>
    </size_fact>
    <size_fact>
      <month>2009-05-01T00:00:00Z</month>
      <code>12938</code>
      <comments>1601</comments>
      <blanks>2267</blanks>
      <comment_ratio>0.110117614691519</comment_ratio>
      <commits>388</commits>
      <man_months>112</man_months>
    </size_fact>
    <size_fact>
      <month>2009-06-01T00:00:00Z</month>
      <code>12937</code>
      <comments>1601</comments>
      <blanks>2267</blanks>
      <comment_ratio>0.110125189159444</comment_ratio>
      <commits>389</commits>
      <man_months>113</man_months>
    </size_fact>
    <size_fact>
      <month>2009-07-01T00:00:00Z</month>
      <code>12941</code>
      <comments>1601</comments>
      <blanks>2267</blanks>
      <comment_ratio>0.110094897538165</comment_ratio>
      <commits>392</commits>
      <man_months>115</man_months>
    </size_fact>
    <size_fact>
      <month>2009-08-01T00:00:00Z</month>
      <code>12960</code>
      <comments>1602</comments>
      <blanks>2274</blanks>
      <comment_ratio>0.110012360939431</comment_ratio>
      <commits>397</commits>
      <man_months>119</man_months>
    </size_fact>
    <size_fact>
      <month>2009-09-01T00:00:00Z</month>
      <code>13002</code>
      <comments>1602</comments>
      <blanks>2276</blanks>
      <comment_ratio>0.109695973705834</comment_ratio>
      <commits>403</commits>
      <man_months>120</man_months>
    </size_fact>
    <size_fact>
      <month>2009-10-01T00:00:00Z</month>
      <code>13002</code>
      <comments>1602</comments>
      <blanks>2276</blanks>
      <comment_ratio>0.109695973705834</comment_ratio>
      <commits>403</commits>
      <man_months>120</man_months>
    </size_fact>
    <size_fact>
      <month>2009-11-01T00:00:00Z</month>
      <code>13045</code>
      <comments>1606</comments>
      <blanks>2279</blanks>
      <comment_ratio>0.109617090983551</comment_ratio>
      <commits>411</commits>
      <man_months>123</man_months>
    </size_fact>
    <size_fact>
      <month>2009-12-01T00:00:00Z</month>
      <code>13045</code>
      <comments>1606</comments>
      <blanks>2279</blanks>
      <comment_ratio>0.109617090983551</comment_ratio>
      <commits>411</commits>
      <man_months>123</man_months>
    </size_fact>
    <size_fact>
      <month>2010-01-01T00:00:00Z</month>
      <code>13046</code>
      <comments>1606</comments>
      <blanks>2279</blanks>
      <comment_ratio>0.10960960960961</comment_ratio>
      <commits>413</commits>
      <man_months>124</man_months>
    </size_fact>
    <size_fact>
      <month>2010-02-01T00:00:00Z</month>
      <code>13071</code>
      <comments>1606</comments>
      <blanks>2281</blanks>
      <comment_ratio>0.10942290658854</comment_ratio>
      <commits>416</commits>
      <man_months>125</man_months>
    </size_fact>
    <size_fact>
      <month>2010-03-01T00:00:00Z</month>
      <code>13071</code>
      <comments>1606</comments>
      <blanks>2281</blanks>
      <comment_ratio>0.10942290658854</comment_ratio>
      <commits>419</commits>
      <man_months>128</man_months>
    </size_fact>
    <size_fact>
      <month>2010-04-01T00:00:00Z</month>
      <code>13148</code>
      <comments>1608</comments>
      <blanks>2287</blanks>
      <comment_ratio>0.108972621306587</comment_ratio>
      <commits>429</commits>
      <man_months>135</man_months>
    </size_fact>
    <size_fact>
      <month>2010-05-01T00:00:00Z</month>
      <code>13477</code>
      <comments>1631</comments>
      <blanks>2306</blanks>
      <comment_ratio>0.107956049774954</comment_ratio>
      <commits>441</commits>
      <man_months>143</man_months>
    </size_fact>
    <size_fact>
      <month>2010-06-01T00:00:00Z</month>
      <code>13747</code>
      <comments>1675</comments>
      <blanks>2323</blanks>
      <comment_ratio>0.108611075087537</comment_ratio>
      <commits>480</commits>
      <man_months>148</man_months>
    </size_fact>
    <size_fact>
      <month>2010-07-01T00:00:00Z</month>
      <code>13756</code>
      <comments>1675</comments>
      <blanks>2324</blanks>
      <comment_ratio>0.108547728598276</comment_ratio>
      <commits>485</commits>
      <man_months>152</man_months>
    </size_fact>
    <size_fact>
      <month>2010-08-01T00:00:00Z</month>
      <code>13760</code>
      <comments>1675</comments>
      <blanks>2324</blanks>
      <comment_ratio>0.108519598315517</comment_ratio>
      <commits>486</commits>
      <man_months>153</man_months>
    </size_fact>
    <size_fact>
      <month>2010-09-01T00:00:00Z</month>
      <code>13760</code>
      <comments>1675</comments>
      <blanks>2324</blanks>
      <comment_ratio>0.108519598315517</comment_ratio>
      <commits>486</commits>
      <man_months>153</man_months>
    </size_fact>
    <size_fact>
      <month>2010-10-01T00:00:00Z</month>
      <code>13793</code>
      <comments>1666</comments>
      <blanks>2325</blanks>
      <comment_ratio>0.107768937188693</comment_ratio>
      <commits>494</commits>
      <man_months>154</man_months>
    </size_fact>
    <size_fact>
      <month>2010-11-01T00:00:00Z</month>
      <code>13803</code>
      <comments>1666</comments>
      <blanks>2325</blanks>
      <comment_ratio>0.107699269506755</comment_ratio>
      <commits>497</commits>
      <man_months>156</man_months>
    </size_fact>
    <size_fact>
      <month>2010-12-01T00:00:00Z</month>
      <code>13818</code>
      <comments>1666</comments>
      <blanks>2325</blanks>
      <comment_ratio>0.107594936708861</comment_ratio>
      <commits>501</commits>
      <man_months>158</man_months>
    </size_fact>
    <size_fact>
      <month>2011-01-01T00:00:00Z</month>
      <code>13818</code>
      <comments>1666</comments>
      <blanks>2325</blanks>
      <comment_ratio>0.107594936708861</comment_ratio>
      <commits>503</commits>
      <man_months>160</man_months>
    </size_fact>
    <size_fact>
      <month>2011-02-01T00:00:00Z</month>
      <code>20011</code>
      <comments>4881</comments>
      <blanks>4172</blanks>
      <comment_ratio>0.196087096255825</comment_ratio>
      <commits>509</commits>
      <man_months>163</man_months>
    </size_fact>
    <size_fact>
      <month>2011-03-01T00:00:00Z</month>
      <code>20347</code>
      <comments>4889</comments>
      <blanks>4212</blanks>
      <comment_ratio>0.193731177682676</comment_ratio>
      <commits>533</commits>
      <man_months>168</man_months>
    </size_fact>
    <size_fact>
      <month>2011-04-01T00:00:00Z</month>
      <code>20417</code>
      <comments>4889</comments>
      <blanks>4211</blanks>
      <comment_ratio>0.193195289654627</comment_ratio>
      <commits>550</commits>
      <man_months>171</man_months>
    </size_fact>
    <size_fact>
      <month>2011-05-01T00:00:00Z</month>
      <code>20417</code>
      <comments>4889</comments>
      <blanks>4211</blanks>
      <comment_ratio>0.193195289654627</comment_ratio>
      <commits>552</commits>
      <man_months>172</man_months>
    </size_fact>
    <size_fact>
      <month>2011-06-01T00:00:00Z</month>
      <code>20417</code>
      <comments>4889</comments>
      <blanks>4211</blanks>
      <comment_ratio>0.193195289654627</comment_ratio>
      <commits>552</commits>
      <man_months>172</man_months>
    </size_fact>
    <size_fact>
      <month>2011-07-01T00:00:00Z</month>
      <code>20417</code>
      <comments>4889</comments>
      <blanks>4211</blanks>
      <comment_ratio>0.193195289654627</comment_ratio>
      <commits>552</commits>
      <man_months>172</man_months>
    </size_fact>
    <size_fact>
      <month>2011-08-01T00:00:00Z</month>
      <code>20417</code>
      <comments>4889</comments>
      <blanks>4211</blanks>
      <comment_ratio>0.193195289654627</comment_ratio>
      <commits>552</commits>
      <man_months>172</man_months>
    </size_fact>
    <size_fact>
      <month>2011-09-01T00:00:00Z</month>
      <code>20417</code>
      <comments>4889</comments>
      <blanks>4211</blanks>
      <comment_ratio>0.193195289654627</comment_ratio>
      <commits>552</commits>
      <man_months>172</man_months>
    </size_fact>
    <size_fact>
      <month>2011-10-01T00:00:00Z</month>
      <code>20417</code>
      <comments>4889</comments>
      <blanks>4211</blanks>
      <comment_ratio>0.193195289654627</comment_ratio>
      <commits>552</commits>
      <man_months>172</man_months>
    </size_fact>
    <size_fact>
      <month>2011-11-01T00:00:00Z</month>
      <code>20419</code>
      <comments>4889</comments>
      <blanks>4211</blanks>
      <comment_ratio>0.193180022127391</comment_ratio>
      <commits>553</commits>
      <man_months>173</man_months>
    </size_fact>
    <size_fact>
      <month>2011-12-01T00:00:00Z</month>
      <code>20419</code>
      <comments>4889</comments>
      <blanks>4211</blanks>
      <comment_ratio>0.193180022127391</comment_ratio>
      <commits>553</commits>
      <man_months>173</man_months>
    </size_fact>
    <size_fact>
      <month>2012-01-01T00:00:00Z</month>
      <code>20490</code>
      <comments>4903</comments>
      <blanks>4227</blanks>
      <comment_ratio>0.1930847083842</comment_ratio>
      <commits>561</commits>
      <man_months>177</man_months>
    </size_fact>
    <size_fact>
      <month>2012-02-01T00:00:00Z</month>
      <code>20521</code>
      <comments>4906</comments>
      <blanks>4227</blanks>
      <comment_ratio>0.192944507806662</comment_ratio>
      <commits>564</commits>
      <man_months>178</man_months>
    </size_fact>
    <size_fact>
      <month>2012-03-01T00:00:00Z</month>
      <code>20521</code>
      <comments>4906</comments>
      <blanks>4227</blanks>
      <comment_ratio>0.192944507806662</comment_ratio>
      <commits>564</commits>
      <man_months>178</man_months>
    </size_fact>
    <size_fact>
      <month>2012-04-01T00:00:00Z</month>
      <code>20551</code>
      <comments>4906</comments>
      <blanks>4229</blanks>
      <comment_ratio>0.192717130848097</comment_ratio>
      <commits>568</commits>
      <man_months>181</man_months>
    </size_fact>
    <size_fact>
      <month>2012-05-01T00:00:00Z</month>
      <code>20551</code>
      <comments>4906</comments>
      <blanks>4229</blanks>
      <comment_ratio>0.192717130848097</comment_ratio>
      <commits>568</commits>
      <man_months>181</man_months>
    </size_fact>
    <size_fact>
      <month>2012-06-01T00:00:00Z</month>
      <code>20551</code>
      <comments>4906</comments>
      <blanks>4229</blanks>
      <comment_ratio>0.192717130848097</comment_ratio>
      <commits>568</commits>
      <man_months>181</man_months>
    </size_fact>
    <size_fact>
      <month>2012-07-01T00:00:00Z</month>
      <code>20551</code>
      <comments>4906</comments>
      <blanks>4229</blanks>
      <comment_ratio>0.192717130848097</comment_ratio>
      <commits>568</commits>
      <man_months>181</man_months>
    </size_fact>
    <size_fact>
      <month>2012-08-01T00:00:00Z</month>
      <code>20573</code>
      <comments>4909</comments>
      <blanks>4230</blanks>
      <comment_ratio>0.192645789184522</comment_ratio>
      <commits>575</commits>
      <man_months>185</man_months>
    </size_fact>
    <size_fact>
      <month>2012-09-01T00:00:00Z</month>
      <code>20573</code>
      <comments>4909</comments>
      <blanks>4230</blanks>
      <comment_ratio>0.192645789184522</comment_ratio>
      <commits>575</commits>
      <man_months>185</man_months>
    </size_fact>
    <size_fact>
      <month>2012-10-01T00:00:00Z</month>
      <code>20573</code>
      <comments>4909</comments>
      <blanks>4230</blanks>
      <comment_ratio>0.192645789184522</comment_ratio>
      <commits>575</commits>
      <man_months>185</man_months>
    </size_fact>
    <size_fact>
      <month>2012-11-01T00:00:00Z</month>
      <code>20588</code>
      <comments>4909</comments>
      <blanks>4230</blanks>
      <comment_ratio>0.192532454798604</comment_ratio>
      <commits>585</commits>
      <man_months>189</man_months>
    </size_fact>
    <size_fact>
      <month>2012-12-01T00:00:00Z</month>
      <code>20610</code>
      <comments>4904</comments>
      <blanks>4232</blanks>
      <comment_ratio>0.192208199419926</comment_ratio>
      <commits>590</commits>
      <man_months>194</man_months>
    </size_fact>
    <size_fact>
      <month>2013-01-01T00:00:00Z</month>
      <code>20616</code>
      <comments>4904</comments>
      <blanks>4233</blanks>
      <comment_ratio>0.192163009404389</comment_ratio>
      <commits>594</commits>
      <man_months>198</man_months>
    </size_fact>
    <size_fact>
      <month>2013-02-01T00:00:00Z</month>
      <code>20616</code>
      <comments>4904</comments>
      <blanks>4233</blanks>
      <comment_ratio>0.192163009404389</comment_ratio>
      <commits>594</commits>
      <man_months>198</man_months>
    </size_fact>
    <size_fact>
      <month>2013-03-01T00:00:00Z</month>
      <code>20448</code>
      <comments>4905</comments>
      <blanks>4247</blanks>
      <comment_ratio>0.193468228611999</comment_ratio>
      <commits>603</commits>
      <man_months>203</man_months>
    </size_fact>
    <size_fact>
      <month>2013-04-01T00:00:00Z</month>
      <code>20444</code>
      <comments>4905</comments>
      <blanks>4245</blanks>
      <comment_ratio>0.19349875734743</comment_ratio>
      <commits>605</commits>
      <man_months>205</man_months>
    </size_fact>
    <size_fact>
      <month>2013-05-01T00:00:00Z</month>
      <code>20444</code>
      <comments>4905</comments>
      <blanks>4245</blanks>
      <comment_ratio>0.19349875734743</comment_ratio>
      <commits>605</commits>
      <man_months>205</man_months>
    </size_fact>
    <size_fact>
      <month>2013-06-01T00:00:00Z</month>
      <code>20444</code>
      <comments>4905</comments>
      <blanks>4245</blanks>
      <comment_ratio>0.19349875734743</comment_ratio>
      <commits>605</commits>
      <man_months>205</man_months>
    </size_fact>
    <size_fact>
      <month>2013-07-01T00:00:00Z</month>
      <code>20444</code>
      <comments>4905</comments>
      <blanks>4245</blanks>
      <comment_ratio>0.19349875734743</comment_ratio>
      <commits>605</commits>
      <man_months>205</man_months>
    </size_fact>
  </result>
</response>
